datanova/__init__.py
datanova/core.py
datanova-0.1.2.dist-info/METADATA
datanova-0.1.2.dist-info/WHEEL
datanova-0.1.2.dist-info/top_level.txt
datanova-0.1.2.dist-info/RECORD
