Metadata-Version: 2.4
Name: DataNova
Version: 0.1.2
Summary: A friendly toolkit for quick exploratory data analysis (EDA)
Author: Riley
License: MIT
Project-URL: Homepage, https://github.com/Riley25/DataNova
Project-URL: Issues, https://github.com/Riley25/DataNova/issues
Keywords: eda,statistics,profiling,regression,visualization,toolkit
Classifier: Programming Language :: Python :: 3
Classifier: License :: OSI Approved :: MIT License
Classifier: Operating System :: OS Independent
Requires-Python: >=3.8
Requires-Dist: pandas
Requires-Dist: numpy
Requires-Dist: matplotlib
Requires-Dist: openpyxl
Requires-Dist: statsmodels
Requires-Dist: pyarrow
Requires-Dist: fastparquet
